dipoleq/__init__.py
dipoleq/__main__.py
dipoleq/_version.py
dipoleq/core.cp313-win_amd64.pyd
dipoleq/ds_names.py
dipoleq/file_input.py
dipoleq/geqdsk.py
dipoleq/h5togeqdsk.py
dipoleq/imas.py
dipoleq/imas_dipole_extras.py
dipoleq/input.py
dipoleq/main_cli.py
dipoleq/plot.py
dipoleq/post_process.py
dipoleq/py.typed
dipoleq/saveh5.py
dipoleq/solver.py
dipoleq/util.py
dipoleq-0.10.2.dist-info/METADATA
dipoleq-0.10.2.dist-info/WHEEL
dipoleq-0.10.2.dist-info/entry_points.txt
dipoleq-0.10.2.dist-info/licenses/LICENSE
dipoleq-0.10.2.dist-info/RECORD
