Metadata-Version: 2.2
Name: dipoleq
Version: 0.10.2
Summary: DipolEq equilibrium solver python bindings.
Author-Email: Darren Garnier <dgarnier@reinrag.net>
Classifier: Development Status :: 4 - Beta
Classifier: License :: OSI Approved :: MIT License
Classifier: Programming Language :: Python :: 3 :: Only
Classifier: Programming Language :: Python :: 3.10
Classifier: Programming Language :: Python :: 3.11
Classifier: Programming Language :: Python :: 3.12
Classifier: Programming Language :: Python :: 3.13
Requires-Python: >=3.10
Requires-Dist: numpy<2.3,>=1.26
Requires-Dist: pydantic<3.0,>=2.10
Requires-Dist: pyyaml
Requires-Dist: types-pyyaml
Requires-Dist: typing-extensions
Requires-Dist: h5py
Requires-Dist: freeqdsk
Requires-Dist: wurlitzer
